jishaku/__init__.py
jishaku/__main__.py
jishaku/codeblocks.py
jishaku/cog.py
jishaku/exception_handling.py
jishaku/flags.py
jishaku/formatting.py
jishaku/functools.py
jishaku/help_command.py
jishaku/hljs.py
jishaku/math.py
jishaku/meta.py
jishaku/models.py
jishaku/modules.py
jishaku/paginators.py
jishaku/py.typed
jishaku/shell.py
jishaku/types.py
jishaku/features/__init__.py
jishaku/features/baseclass.py
jishaku/features/filesystem.py
jishaku/features/guild.py
jishaku/features/invocation.py
jishaku/features/management.py
jishaku/features/python.py
jishaku/features/root_command.py
jishaku/features/shell.py
jishaku/features/sql.py
jishaku/features/voice.py
jishaku/features/youtube.py
jishaku/features/scaffolds/cargo/Cargo.toml
jishaku/features/scaffolds/cargo/src/main.rs
jishaku/features/scaffolds/npm/index.js
jishaku/features/scaffolds/npm/package.json
jishaku/features/scaffolds/pyright/main.py
jishaku/features/scaffolds/pyright/pyrightconfig.json
jishaku/repl/__init__.py
jishaku/repl/compilation.py
jishaku/repl/disassembly.py
jishaku/repl/inspections.py
jishaku/repl/repl_builtins.py
jishaku/repl/scope.py
jishaku/repl/walkers.py
Aniflax-1.0.0.dist-info/LICENSE
Aniflax-1.0.0.dist-info/METADATA
Aniflax-1.0.0.dist-info/WHEEL
Aniflax-1.0.0.dist-info/entry_points.txt
Aniflax-1.0.0.dist-info/top_level.txt
Aniflax-1.0.0.dist-info/RECORD
