Metadata-Version: 2.1
Name: Aniflax
Version: 1.0.0
Summary: A discord.py extension including useful tools for bot development and debugging.
Home-page: https://github.com/nitrixly/Aniflax
Download-URL: https://github.com/scarletcafe/jishaku/archive/2.6.0.tar.gz
Author: Nitrix
License: MIT
Project-URL: Documentation, https://jishaku.readthedocs.io/en/latest/
Project-URL: Code, https://github.com/nitrixly/Aniflax
Project-URL: Issue tracker, https://github.com/scarletcafe/jishaku/issues
Keywords: Aniflax discord.py discord cog repl extension
Classifier: Development Status :: 5 - Production/Stable
Classifier: Framework :: AsyncIO
Classifier: Intended Audience :: Developers
Classifier: License :: OSI Approved :: MIT License
Classifier: Natural Language :: English
Classifier: Operating System :: OS Independent
Classifier: Programming Language :: Python :: 3 :: Only
Classifier: Programming Language :: Python :: 3.8
Classifier: Programming Language :: Python :: 3.9
Classifier: Programming Language :: Python :: 3.10
Classifier: Programming Language :: Python :: 3.11
Classifier: Programming Language :: Python :: 3.12
Classifier: Topic :: Communications :: Chat
Classifier: Topic :: Internet
Classifier: Topic :: Software Development :: Debuggers
Classifier: Topic :: Software Development :: Testing
Classifier: Topic :: Utilities
Requires-Python: >=3.8.0
License-File: LICENSE
Requires-Dist: braceexpand >=0.1.7
Requires-Dist: click >=8.1.7
Requires-Dist: discord.py >=2.4.0
Requires-Dist: import-expression <3.0.0,>=2.0.0
Requires-Dist: tabulate >=0.9.0
Requires-Dist: typing-extensions <5,>=4.3
Requires-Dist: importlib-metadata >=3.7.0 ; python_version < "3.10"
Provides-Extra: docs
Requires-Dist: Sphinx >=4.4.0 ; extra == 'docs'
Requires-Dist: sphinxcontrib-trio >=1.1.2 ; extra == 'docs'
Provides-Extra: procinfo
Requires-Dist: psutil >=5.9.5 ; extra == 'procinfo'
Provides-Extra: profiling
Requires-Dist: line-profiler >=4.1.1 ; extra == 'profiling'
Provides-Extra: publish
Requires-Dist: Jinja2 >=3.1.2 ; extra == 'publish'
Provides-Extra: test
Requires-Dist: coverage >=7.3.2 ; extra == 'test'
Requires-Dist: flake8 >=6.1.0 ; extra == 'test'
Requires-Dist: isort >=5.12.0 ; extra == 'test'
Requires-Dist: pylint >=3.0.1 ; extra == 'test'
Requires-Dist: pytest >=7.4.2 ; extra == 'test'
Requires-Dist: pytest-asyncio >=0.21.0 ; extra == 'test'
Requires-Dist: pytest-cov >=4.1.0 ; extra == 'test'
Requires-Dist: pytest-mock >=3.11.1 ; extra == 'test'
Provides-Extra: voice
Requires-Dist: discord.py[voice] >=2.3.2 ; extra == 'voice'
Requires-Dist: yt-dlp >=2023.10.13 ; extra == 'voice'
